.coveragerc
CHANGES.rst
COPYRIGHT.txt
DOCS.rst
HACKING.rst
LICENSE.txt
OLD_CHANGES.rst
README.rst
TODO.rst
buildout.cfg
setup.py
src/icemac/__init__.py
src/icemac.callonchange.egg-info/PKG-INFO
src/icemac.callonchange.egg-info/SOURCES.txt
src/icemac.callonchange.egg-info/dependency_links.txt
src/icemac.callonchange.egg-info/entry_points.txt
src/icemac.callonchange.egg-info/namespace_packages.txt
src/icemac.callonchange.egg-info/not-zip-safe
src/icemac.callonchange.egg-info/requires.txt
src/icemac.callonchange.egg-info/top_level.txt
src/icemac/callonchange/__init__.py
src/icemac/callonchange/observer.py
src/icemac/callonchange/recipe.py
src/icemac/callonchange/script.py
src/icemac/callonchange/testing.py
src/icemac/callonchange/tests/__init__.py
src/icemac/callonchange/tests/bugfix.txt
src/icemac/callonchange/tests/recipe.txt
src/icemac/callonchange/tests/test_directory_observer.py
src/icemac/callonchange/tests/test_file_observer.py
src/icemac/callonchange/tests/test_mangle.py
src/icemac/callonchange/tests/test_recipe.py