Metadata-Version: 2.1
Name: icemac.callonchange
Version: 0.8
Summary: Call a command when a directory or file has changed. (Mac OS only)
Home-page: http://pypi.python.org/icemac.callonchange
Author: Michael Howitz
Author-email: icemac@gmx.net
License: MIT
Keywords: mac os event fs filesystem call change command tdd test driven development
Platform: UNKNOWN
Classifier: Development Status :: 4 - Beta
Classifier: Environment :: Console
Classifier: Environment :: MacOS X
Classifier: Framework :: Buildout :: Recipe
Classifier: Intended Audience :: Developers
Classifier: License :: OSI Approved :: MIT License
Classifier: Natural Language :: English
Classifier: Operating System :: MacOS :: MacOS X
Classifier: Programming Language :: Python
Classifier: Programming Language :: Python :: 2 :: Only
Classifier: Programming Language :: Python :: 2.7
Classifier: Topic :: Software Development :: Testing
Classifier: Topic :: Utilities
Provides-Extra: test
